og_kernel/__init__.py
og_kernel/kernel/__init__.py
og_kernel/kernel/config.py
og_kernel/kernel/kernel_app.py
og_kernel/kernel/kernel_client.py
og_kernel/kernel/kernel_mgr.py
og_kernel/kernel/launch_kernel.py
og_kernel/server/__init__.py
og_kernel/server/kernel_rpc_server.py
og_kernel-0.5.3.dist-info/METADATA
og_kernel-0.5.3.dist-info/WHEEL
og_kernel-0.5.3.dist-info/entry_points.txt
og_kernel-0.5.3.dist-info/top_level.txt
og_kernel-0.5.3.dist-info/RECORD
